cbp_client/__init__.py
cbp_client/api.py
cbp_client/api_authenticated.py
cbp_client/api_public.py
cbp_client/auth.py
cbp_client/helpers.py
cbp_client/history.py
cbp_client/pagination.py
cbp_client/product.py
cbp_client-1.1.4.dist-info/LICENSE
cbp_client-1.1.4.dist-info/METADATA
cbp_client-1.1.4.dist-info/WHEEL
cbp_client-1.1.4.dist-info/top_level.txt
cbp_client-1.1.4.dist-info/RECORD
