Metadata-Version: 2.1
Name: cbp-client
Version: 1.1.4
Summary: An unofficial python package for interacting with the Coinbase Pro API
Home-page: https://github.com/TerrellV/python-coinbasepro
Author: TerrellV
Author-email: terrell.vest@gmail.com
License: UNKNOWN
Project-URL: Bug Tracker, https://github.com/TerrellV/python-coinbasepro/issues
Keywords: coinbase,coinbase pro,cbp,crypto,bitcoin,coinbasepro,python,api
Platform: UNKNOWN
Classifier: Programming Language :: Python :: 3
Classifier: License :: OSI Approved :: MIT License
Classifier: Operating System :: OS Independent
Requires-Python: >=3.6
License-File: LICENSE
Requires-Dist: requests (==2.25.1)
